payway/__init__.py
payway/client.py
payway/conf.py
payway/constants.py
payway/customers.py
payway/exceptions.py
payway/model.py
payway/test_utils.py
payway/transactions.py
payway/utils.py
python_payway-0.0.5.dist-info/LICENSE
python_payway-0.0.5.dist-info/METADATA
python_payway-0.0.5.dist-info/WHEEL
python_payway-0.0.5.dist-info/top_level.txt
python_payway-0.0.5.dist-info/RECORD
