Metadata-Version: 2.1
Name: python-payway
Version: 0.0.5
Summary: Python client for working with Westpac's PayWay REST API
Author-email: Ben Napper <reppan197@gmail.com>
License: MIT
Keywords: payway,westpac,api,client
Classifier: Programming Language :: Python :: 3
Classifier: License :: OSI Approved :: MIT License
Classifier: Operating System :: OS Independent
Requires-Python: >=3.8
License-File: LICENSE
Requires-Dist: requests>=2.20.0
Provides-Extra: dev
Requires-Dist: pre-commit>=3.5.0; extra == "dev"
Requires-Dist: ruff==0.6.6; extra == "dev"
Requires-Dist: mypy>=0.971; extra == "dev"
